MOFClassifier/CLscore.py
MOFClassifier/__init__.py
MOFClassifier-0.1.1.dist-info/LICENSE
MOFClassifier-0.1.1.dist-info/METADATA
MOFClassifier-0.1.1.dist-info/WHEEL
MOFClassifier-0.1.1.dist-info/top_level.txt
MOFClassifier-0.1.1.dist-info/RECORD
