Metadata-Version: 2.1
Name: MOFClassifier
Version: 0.1.1
Summary: A Machine Learning Approach for Validating Computation-Ready Metal-Organic Frameworks
Home-page: https://github.com/Chung-Research-Group/MOFClassifier
Author: Guobin Zhao
Author-email: sxmzhaogb@gmai.com
License: CC-BY-4.0
Classifier: Development Status :: 5 - Production/Stable
Classifier: Intended Audience :: Developers
Classifier: Topic :: Scientific/Engineering :: Chemistry
Classifier: Programming Language :: Python :: 3.9
Requires-Python: >=3.9, <4
License-File: LICENSE
Requires-Dist: ase
Requires-Dist: numpy==1.26.4
Requires-Dist: torch==2.7.0
Requires-Dist: Pymatgen==2024.8.9
Requires-Dist: scikit-learn==1.3.2
Requires-Dist: tqdm==4.67.1
Requires-Dist: pandas==2.2.3
